pyprost/__init__.py
pyprost/esmts25_13.py
pyprost/prosttools.py
pyprost-0.2.16.data/scripts/prost.py
pyprost-0.2.16.dist-info/LICENSE
pyprost-0.2.16.dist-info/METADATA
pyprost-0.2.16.dist-info/WHEEL
pyprost-0.2.16.dist-info/top_level.txt
pyprost-0.2.16.dist-info/RECORD
