Metadata-Version: 2.1
Name: pyprost
Version: 0.2.16
Summary: PRotein Ortholog Search Tool
Home-page: https://github.com/mesihk/prost
Author: Mesih Kilinc
Author-email: mesih@iastate.edu
Project-URL: Bug Tracker, https://github.com/mesihk/prost/issues
Classifier: Programming Language :: Python :: 3
Classifier: License :: OSI Approved :: MIT License
Classifier: Operating System :: OS Independent
Requires-Python: >=3.8
License-File: LICENSE
Requires-Dist: numpy
Requires-Dist: scipy
Requires-Dist: click
Requires-Dist: blosc
Requires-Dist: torch
Requires-Dist: fair-esm
Requires-Dist: statsmodels
